<?xml version="1.0"?>
<!DOCTYPE datafile PUBLIC "-//Logiqx//DTD ROM Management Datafile//EN" "http://www.logiqx.com/Dats/datafile.dtd">
<datafile>
	<header>
		<name>Pure DOS DAT - Unverified Variants - Install Media</name>
		<description>DOS Game Install Media</description>
		<version>2025-05-01 00-00-00</version>
		<date>2025-05-01 00-00-00</date>
		<author>Pure DOS DAT</author>
		<homepage>Pure DOS DAT</homepage>
		<url>https://github.com/PureDOS/DAT</url>
	</header>
	<game name="Settlers II, The (1996) (Blue Byte Software) (Installation).dosz">
		<description>Settlers II, The</description>
		<comment>Redump-verified CD-ROM: Bravo ScreenFun 10/2002 (Germany)</comment>
		<year>1996</year>
		<developer>Blue Byte Software</developer>
		<variant>Installation</variant>
		<link type="media">http://redump.org/disc/38196/</link>
		<rom name="Bravo ScreenFun 10-2002 (Germany).chd" size="823056768" crc="b910367d" md5="922175aa4f05760be4e135eb1a36618c" sha1="aee114cca98e45eb3c82e12385d2ae363c441acf">
			<track number="1" type="MODE1_RAW" frames="215298" pregap="0" duration="47:50:48" size="506380896" crc="9473bf16" md5="bb38b5ee9e415963fa8e3c69701e9554" sha1="726217d8331dfdb3dfd6ee435b2e438d3ae0f8a0"/>
			<track number="2" type="AUDIO" frames="11546" pregap="150" duration="02:33:71" size="27156192" crc="7a92de1e" md5="70bce6295dca1d748a699f322d42b5f3" sha1="c0c32eb1ab16f7b7759ce48c9542139a05c66877" in_zeros="894044" out_zeros="4474" trimmed_crc="5faa9d8b"/>
			<track number="3" type="AUDIO" frames="13430" pregap="149" duration="02:59:05" size="31587360" crc="05a9e25f" md5="5d11d31453f2e63be5a2d2dffeb7f34f" sha1="b33abeba95537b4227a97c4a9b1298ebb34629be" in_zeros="891756" out_zeros="4473" trimmed_crc="f761ba7e"/>
			<track number="4" type="AUDIO" frames="13049" pregap="149" duration="02:53:74" size="30691248" crc="e2e148e8" md5="44a54691120f75a012ab5b72dba4568a" sha1="2399c790acd479ea2a137015c3fb24b065a4852d" in_zeros="891756" out_zeros="4472" trimmed_crc="9c60eeb2"/>
			<track number="5" type="AUDIO" frames="12978" pregap="149" duration="02:53:03" size="30524256" crc="eff05488" md5="72708532a4f159e7f8e21b8955800528" sha1="05f0c98f50013a9638b225c7d7fcb46e07f8117b" in_zeros="891756" out_zeros="4473" trimmed_crc="bdc5d4f7"/>
			<track number="6" type="AUDIO" frames="16765" pregap="149" duration="03:43:40" size="39431280" crc="2db1070e" md5="3b556bb11deb1fb75773744051dc9db6" sha1="e1ede02edf5ad2ad147c41bf3635919b7ed69317" in_zeros="891756" out_zeros="4472" trimmed_crc="e7f512f9"/>
			<track number="7" type="AUDIO" frames="33219" pregap="149" duration="07:22:69" size="78131088" crc="60e23427" md5="b18a9df2c493309eaf2039850374c6c3" sha1="143df0926e93c5b402ec4b9d533481a5672a6a10" in_zeros="891756" out_zeros="4473" trimmed_crc="34e82784"/>
			<track number="8" type="AUDIO" frames="9656" pregap="149" duration="02:08:56" size="22710912" crc="eb3a995d" md5="d44d4a681e9ac48d33831057efecc6a0" sha1="9819007a6fca72a743a1dd3b7c122e3e09f67d4c" in_zeros="891756" out_zeros="4473" trimmed_crc="3262fa5b"/>
			<track number="9" type="AUDIO" frames="13179" pregap="149" duration="02:55:54" size="30997008" crc="3b518a75" md5="b3684a6a9c2836a84c10258de219df8f" sha1="09dee234efe2fd13d2f04a81d736cd57d9d03bc1" in_zeros="891756" out_zeros="2120" trimmed_crc="0d1bd4f5"/>
		</rom>
	</game>
	<game name="Siedler II, Die (1996) (Blue Byte Software) (Installation).dosz">
		<description>Siedler II, Die</description>
		<comment>Redump-verified CD-ROM: Siedler II, Die - Gold Edition (Germany) (Rerelease) (2000-03-08)</comment>
		<year>1996</year>
		<developer>Blue Byte Software</developer>
		<variant>Installation</variant>
		<link type="media">http://redump.org/disc/68730/</link>
		<rom name="Siedler II, Die - Gold Edition (Germany) (Rerelease) (2000-03-08).chd" size="551563776" crc="4e2014b7" md5="0502039ad8fea64c181fad472b9550a0" sha1="71602f9f8a1dc48a4dc9d6d2b6c97c105634fa47">
			<track number="1" type="MODE1_RAW" frames="104211" pregap="0" duration="23:09:36" size="245104272" crc="fcdcab71" md5="286c96f5daabfbfad8f06e5630d7c1fb" sha1="c0e52c5a90c16cb6bc9a75f58c44cc51d66633c9"/>
			<track number="2" type="AUDIO" frames="11846" pregap="151" duration="02:37:71" size="27861792" crc="b0c6c3c8" md5="d0ef1330c80f7009ab461bd13030dc6c" sha1="07d33efa2058e0308384fcdf220d43633d75f0c7" in_zeros="1" out_zeros="361527" trimmed_crc="264e2dbb"/>
			<track number="3" type="AUDIO" frames="13580" pregap="149" duration="03:01:05" size="31940160" crc="b146d762" md5="f9bea75962264cc7f5cfca15823cbc1f" sha1="c2b6005768b08ca522963d928bcf4298937e1f5b" in_zeros="886396" out_zeros="362410" trimmed_crc="42f1ac97"/>
			<track number="4" type="AUDIO" frames="13241" pregap="149" duration="02:56:41" size="31142832" crc="a87ff1f8" md5="12af3fff1fd75fbc4bd71260b193443f" sha1="6c94be638c68a41ee37c8c6213ebbccd66aab324" in_zeros="886396" out_zeros="358733" trimmed_crc="06da92c3"/>
			<track number="5" type="AUDIO" frames="13180" pregap="149" duration="02:55:55" size="30999360" crc="bf16ef85" md5="6d5115019f1eaec98ee81d7eb0f81cea" sha1="c6c2bb0ebd5c68205ed25f83c3222dad2121985b" in_zeros="886396" out_zeros="363759" trimmed_crc="d03f7c5b"/>
			<track number="6" type="AUDIO" frames="16969" pregap="149" duration="03:46:19" size="39911088" crc="21e60cc3" md5="9ba8e867a85acccd94aeccefdcd6925a" sha1="6e7683faabfa2ad9b623ea4370bdb6bcde815e63" in_zeros="886396" out_zeros="367259" trimmed_crc="28b87954"/>
			<track number="7" type="AUDIO" frames="33392" pregap="149" duration="07:25:17" size="78537984" crc="afec9b57" md5="f482051788156e6b49ffc6822459bcb2" sha1="92be77923c56a2333132079743eaf2a2471819d8" in_zeros="886396" out_zeros="359125" trimmed_crc="51af0dc4"/>
			<track number="8" type="AUDIO" frames="9819" pregap="149" duration="02:10:69" size="23094288" crc="c7673dcc" md5="91979c207684aa86bc0f24edb6541d8b" sha1="98ffac15154face57e3817d65bb8b1008adf8549" in_zeros="886396" out_zeros="359616" trimmed_crc="b0bee92e"/>
			<track number="9" type="AUDIO" frames="13200" pregap="149" duration="02:56:00" size="31046400" crc="bd8f80e0" md5="53c3e4e33ae829b8c2c9ccbbb27335a6" sha1="98fa9b475844dbdf796f49dbc04e86dca779cfa0" in_zeros="886396" out_zeros="355152" trimmed_crc="71105ed8"/>
		</rom>
	</game>
</datafile>
